rs_bytepiece-0.2.2.dist-info/METADATA
rs_bytepiece-0.2.2.dist-info/WHEEL
rs_bytepiece-0.2.2.dist-info/license_files/LICENSE
rs_bytepiece/__init__.py
rs_bytepiece/rs_bytepiece.pyd
rs_bytepiece-0.2.2.dist-info/RECORD
